CorrDim_By_Bisca/__init__.py
CorrDim_By_Bisca/corrdim.py
CorrDim_By_Bisca/dimensionality.py
idPettis_By_Bisca/__init__.py
idPettis_By_Bisca/idpettis_By_Bisca.py
CorrDim_By_Bisca-0.0.3.dist-info/LICENSE.txt
CorrDim_By_Bisca-0.0.3.dist-info/METADATA
CorrDim_By_Bisca-0.0.3.dist-info/WHEEL
CorrDim_By_Bisca-0.0.3.dist-info/top_level.txt
CorrDim_By_Bisca-0.0.3.dist-info/RECORD
