Metadata-Version: 2.1
Name: CorrDim_By_Bisca
Version: 0.0.3
Summary: Python module for dimensionality analysis using CorrDim and related algorithms
Author: Eng. Alberto Biscalchin
Author-email: biscalchin.mau.se@gmail.com
Keywords: correlation dimension,CorrDim algorithm,fractal analysis,chaos theory,data analysis,NumPy,SciPy,multidimensional scaling,time-series analysis,packing numbers,local dimension
Classifier: Development Status :: 4 - Beta
Classifier: Intended Audience :: Science/Research
Classifier: Programming Language :: Python :: 3
Classifier: Operating System :: OS Independent
License-File: LICENSE.txt
Requires-Dist: numpy
Requires-Dist: scipy
Requires-Dist: scikit-learn
